cbases/__init__.py
cbases/core.py
cbases-1.0.3.dist-info/licenses/LICENSE
cbases-1.0.3.dist-info/WHEEL
cbases-1.0.3.dist-info/METADATA
cbases-1.0.3.dist-info/RECORD
