Metadata-Version: 2.4
Name: cbases
Version: 1.0.3
Summary: Number base conversion library with Roman numeral support
Keywords: base,conversion,roman,numerals,mathematics
Author-email: MagnusGabinus <magnusgabinus@protonmail.com>
Requires-Python: >=3.7
Classifier: Programming Language :: Python :: 3
Classifier: License :: OSI Approved :: MIT License
Classifier: Operating System :: OS Independent
License-File: LICENSE
Project-URL: Homepage, https://github.com/MagnusGabinus/cbases
